celestial.py
command.py
create_files.py
error.py
setup.py
cosmic_framework.egg-info/PKG-INFO
cosmic_framework.egg-info/SOURCES.txt
cosmic_framework.egg-info/dependency_links.txt
cosmic_framework.egg-info/entry_points.txt
cosmic_framework.egg-info/requires.txt
cosmic_framework.egg-info/top_level.txt