Metadata-Version: 1.0
Name: cosmic-framework
Version: 1.0
Summary: A simple backend framework built using python
Home-page: UNKNOWN
Author: Aryaan Hegde
Author-email: aryhegde@gmail.com
License: UNKNOWN
Platform: UNKNOWN
